nhentaidevs/__init__.py
nhentaidevs/__main__.py
nhentaidevs/browgine.py
nhentaidevs-1.2.0.dist-info/METADATA
nhentaidevs-1.2.0.dist-info/WHEEL
nhentaidevs-1.2.0.dist-info/top_level.txt
nhentaidevs-1.2.0.dist-info/RECORD
