Metadata-Version: 2.1
Name: nhentaidevs
Version: 1.2.0
Summary: Mini Nhentai Doujins Scraper/Downloader.
Home-page: https://pypi.org/project/nhentaidevs
Author: John Lester Dev :>
Author-email: johnlesterincbusiness@gmail.com
License: UNKNOWN
Keywords: nhentai,download,images,doujinshi,cli,scraper
Platform: UNKNOWN
Classifier: Programming Language :: Python :: 3
Classifier: Operating System :: OS Independent
Requires-Python: >=3.8
Requires-Dist: beautifulsoup4
Requires-Dist: coloredevs
Requires-Dist: requests
Requires-Dist: pickle-mixin
Requires-Dist: click
Requires-Dist: tqdm
